nobiserviceslib/__init__.py
nobiserviceslib/nobi_file.py
nobiserviceslib/encryption/RSAPlusAES.py
nobiserviceslib/encryption/__init__.py
nobiserviceslib/encryption/nobi_cipher.py
nobiserviceslib/internet/Errors.py
nobiserviceslib/internet/HttpConection.py
nobiserviceslib/internet/__init__.py
nobiserviceslib/internet/nobi_inet.py
nobiserviceslib-0.1.4.dist-info/METADATA
nobiserviceslib-0.1.4.dist-info/WHEEL
nobiserviceslib-0.1.4.dist-info/top_level.txt
nobiserviceslib-0.1.4.dist-info/RECORD
