Metadata-Version: 2.1
Name: nobiserviceslib
Version: 0.1.4
Summary: NobiServices Python API.
Home-page: https://github.com/GuavaAndNobi/NobiServicesLib-Python
Author: Guava and Nobi
Maintainer: Guava and Nobi
License: LGPL
Platform: all
Requires-Dist: dnspython (>=1.16.0)
Requires-Dist: pycryptodome (>=3.9.6)
